sa002package/__init__.py
sa002package/exfn001add.py
sa002package/exfn001add_release.py
sa002package/pytransform/__init__.py
sa002package/pytransform/_pytransform.dylib
standalone002pyarmor-0.0.35.dist-info/LICENSE
standalone002pyarmor-0.0.35.dist-info/METADATA
standalone002pyarmor-0.0.35.dist-info/WHEEL
standalone002pyarmor-0.0.35.dist-info/top_level.txt
standalone002pyarmor-0.0.35.dist-info/RECORD
